timed_sparse_matrix/TSMDLL.dll
timed_sparse_matrix/__init__.py
timed_sparse_matrix/timed_sparse_matrix.py
timed_sparse_matrix-0.1.2.dist-info/LICENSE.txt
timed_sparse_matrix-0.1.2.dist-info/METADATA
timed_sparse_matrix-0.1.2.dist-info/WHEEL
timed_sparse_matrix-0.1.2.dist-info/top_level.txt
timed_sparse_matrix-0.1.2.dist-info/RECORD
