Metadata-Version: 2.1
Name: timed_sparse_matrix
Version: 0.1.2
Summary: Loading and saving timed sparse tensors.
Author-email: Anton R Sobinov <an.sobinov@gmail.com>
Project-URL: Homepage, https://github.com/nishbo/timed_sparse_matrix
Classifier: Programming Language :: Python :: 3
Classifier: License :: OSI Approved :: GNU General Public License v3 (GPLv3)
Classifier: Operating System :: Microsoft :: Windows
Classifier: Development Status :: 5 - Production/Stable
Classifier: Environment :: Console
Requires-Python: >=3.7
License-File: LICENSE.txt
Requires-Dist: numpy
